{
    "$schema": "../Schema.json",
    "Name": "RolePermissionGroupMappings",
    "AddAdditionalColumns": true,
    "Columns": [
        {"Name": "Role", "Datatype": "Integer", "IsRequired": true, "IsForeignKey": true, "ForeignName": "Id", "ForeignSchema": "Levendr", "ForeignTable": "Roles"},
        {"Name": "PermissionGroup", "Datatype": "Integer", "IsRequired": true, "IsForeignKey": true, "ForeignName": "Id", "ForeignSchema": "Levendr", "ForeignTable": "PermissionGroups"},
        {"Name": "UserLevelAccess", "Datatype": "Integer", "IsRequired": true, "IsForeignKey": true, "ForeignName": "Id", "ForeignSchema": "Levendr", "ForeignTable": "UserLevelAccess"},
        {"Name": "IsSystem", "Datatype": "Boolean", "IsRequired": true}
    ],
    "DefaultRows": [
        {"Role": 1, "PermissionGroup": 1, "UserLevelAccess": 1, "IsSystem": true},
        {"Role": 1, "PermissionGroup": 3, "UserLevelAccess": 1, "IsSystem": true},
        {"Role": 1, "PermissionGroup": 5, "UserLevelAccess": 1, "IsSystem": true},
        {"Role": 1, "PermissionGroup": 7, "UserLevelAccess": 1, "IsSystem": true},
        {"Role": 1, "PermissionGroup": 9, "UserLevelAccess": 1, "IsSystem": true},
        {"Role": 1, "PermissionGroup": 11, "UserLevelAccess": 1, "IsSystem": true},
        {"Role": 1, "PermissionGroup": 13, "UserLevelAccess": 1, "IsSystem": true},
        {"Role": 1, "PermissionGroup": 15, "UserLevelAccess": 1, "IsSystem": true},
        {"Role": 1, "PermissionGroup": 17, "UserLevelAccess": 1, "IsSystem": true},
        {"Role": 1, "PermissionGroup": 19, "UserLevelAccess": 1, "IsSystem": true},
        
        {"Role": 2, "PermissionGroup": 2, "UserLevelAccess": 1, "IsSystem": true},
        {"Role": 2, "PermissionGroup": 4, "UserLevelAccess": 1, "IsSystem": true},
        {"Role": 2, "PermissionGroup": 6, "UserLevelAccess": 1, "IsSystem": true},
        {"Role": 2, "PermissionGroup": 8, "UserLevelAccess": 1, "IsSystem": true},
        {"Role": 2, "PermissionGroup": 10, "UserLevelAccess": 1, "IsSystem": true},
        {"Role": 2, "PermissionGroup": 12, "UserLevelAccess": 1, "IsSystem": true},
        {"Role": 2, "PermissionGroup": 14, "UserLevelAccess": 1, "IsSystem": true},
        {"Role": 2, "PermissionGroup": 15, "UserLevelAccess": 1, "IsSystem": true},
        {"Role": 2, "PermissionGroup": 17, "UserLevelAccess": 1, "IsSystem": true},        
        {"Role": 2, "PermissionGroup": 20, "UserLevelAccess": 1, "IsSystem": true},
        
        {"Role": 3, "PermissionGroup": 16, "UserLevelAccess": 2, "IsSystem": true},
        {"Role": 3, "PermissionGroup": 18, "UserLevelAccess": 2, "IsSystem": true}
    ]
}