{
    "Info":
    {
        "Users": "Users",
        "Roles": "Roles",
        "UserRoles": "UserRoles",
        "Permissions": "Permissions",
        "RolePermissions": "RolePermissions",
        "PermissionGroups": "PermissionGroups",
        "PermissionGroupMapping": "PermissionGroupMapping",
        "RolePermissionGroupMapping": "RolePermissionGroupMapping",
        "ForeignData": "ForeignData",
        "InsertionSettings": "InsertionSettings",
        "Settings": "Settings",
        "MediaSources": "MediaSources",
        "Media": "Media",
        "Templates": "Templates",
        "Categories": "Categories",
        "Pages": "Pages",
        "PageRoles": "PageRoles",
        "Posts": "Posts"
    }
}